<titlelist>
	<!-- 称号说明（同成就）
	title_id 称号id
	title_name 称号名称
	category 称号标签（暂时不做）
	title_img 美术资源名
	nature_act 激活属性  nature_eqp 佩戴属性  att_type 属性类型 att_value 属性值 -->

<!--到达等级的成就-->
  <titlelist title_id="1" category="1" title_name="至高战神" desc="活动专属" title_img="icon_title_ui_1">
    	<nature_act att_type="14" att_value="2000"/> 	
		<nature_act att_type="5" att_value="44"/>
		<nature_act att_type="38" att_value="55"/>	
		<nature_eqp att_type="30" att_value="5"/>
  </titlelist>
  <titlelist title_id="2" category="1" title_name="灭世暴君" desc="活动专属" title_img="icon_title_ui_2">
    	<nature_act att_type="14" att_value="3000"/> 	
		<nature_act att_type="5" att_value="32"/>
		<nature_act att_type="38" att_value="40"/>	
		<nature_eqp att_type="19" att_value="5"/>
  </titlelist>
  <titlelist title_id="3" category="1" title_name="最终帝王" desc="活动专属" title_img="icon_title_ui_3">
    	<nature_act att_type="14" att_value="3500"/> 	
		<nature_act att_type="5" att_value="30"/>
		<nature_act att_type="38" att_value="45"/>	
		<nature_eqp att_type="22" att_value="50"/>
  </titlelist>
  <titlelist title_id="4" category="2" title_name="弑神者" desc="尽请期待" title_img="icon_title_ui_4">
    	<nature_act att_type="14" att_value="2800"/> 	
		<nature_act att_type="38" att_value="32"/>
		<nature_act att_type="5" att_value="48"/>	
		<nature_eqp att_type="38" att_value="32"/>
		<nature_eqp att_type="5" att_value="48"/>
  </titlelist>
  <titlelist title_id="5" category="2" title_name="暗影使徒" desc="尽请期待" title_img="icon_title_ui_5">
    	<nature_act att_type="14" att_value="2800"/> 	
		<nature_act att_type="38" att_value="32"/>
		<nature_act att_type="5" att_value="48"/>	
		<nature_eqp att_type="38" att_value="32"/>
		<nature_eqp att_type="5" att_value="48"/>
  </titlelist>
  <titlelist title_id="6" category="2" title_name="大魔导师" desc="尽请期待" title_img="icon_title_ui_6">
    	<nature_act att_type="14" att_value="2800"/> 	
		<nature_act att_type="38" att_value="32"/>
		<nature_act att_type="5" att_value="48"/>	
		<nature_eqp att_type="38" att_value="32"/>
		<nature_eqp att_type="5" att_value="48"/>
  </titlelist>
  <titlelist title_id="7" category="1" title_name="神殿骑士" desc="尽请期待" title_img="icon_title_ui_7">
    	<nature_act att_type="14" att_value="2800"/> 	
		<nature_act att_type="38" att_value="32"/>
		<nature_act att_type="5" att_value="48"/>	
		<nature_eqp att_type="38" att_value="32"/>
		<nature_eqp att_type="5" att_value="48"/>
  </titlelist>
  <titlelist title_id="8" category="1" title_name="军团统领" desc="尽请期待" title_img="icon_title_ui_8">
    	<nature_act att_type="14" att_value="2800"/> 	
		<nature_act att_type="38" att_value="32"/>
		<nature_act att_type="5" att_value="48"/>	
		<nature_eqp att_type="38" att_value="32"/>
		<nature_eqp att_type="5" att_value="48"/>
  </titlelist>
  <titlelist title_id="9" category="1" title_name="仲裁之力" desc="活动专属" title_img="icon_title_ui_9">
    	<nature_act att_type="14" att_value="1500"/> 
    	<nature_act att_type="15" att_value="1500"/> 		
		<nature_act att_type="5" att_value="20"/>
		<nature_act att_type="38" att_value="30"/>	
		<nature_eqp att_type="44" att_value="20"/>
  </titlelist>
  <titlelist title_id="10" category="1" title_name="黎明之光" desc="尽请期待" title_img="icon_title_ui_10">
    	<nature_act att_type="14" att_value="2800"/> 	
		<nature_act att_type="38" att_value="32"/>
		<nature_act att_type="5" att_value="48"/>	
		<nature_eqp att_type="38" att_value="32"/>
		<nature_eqp att_type="5" att_value="48"/>
  </titlelist>
  <titlelist title_id="11" category="1" title_name="亿万富豪" desc="活动专属" title_img="icon_title_ui_11">
    	<nature_act att_type="14" att_value="1500"/> 	
		<nature_act att_type="38" att_value="30"/>
		<nature_act att_type="5" att_value="40"/>	
		<nature_eqp att_type="15" att_value="1000"/>
  </titlelist>
  <titlelist title_id="12" category="1" title_name="挥金如土" desc="活动专属" title_img="icon_title_ui_12">
    	<nature_act att_type="14" att_value="1600"/> 	
		<nature_act att_type="38" att_value="28"/>
		<nature_act att_type="5" att_value="38"/>	
		<nature_eqp att_type="14" att_value="500"/>
  </titlelist>
  <titlelist title_id="13" category="1" title_name="天启城主" desc="占领天启城后获得" title_img="icon_title_ui_13">
		<nature_act att_type="38" att_value="100"/>
		<nature_act att_type="5" att_value="100"/>	
		<nature_eqp att_type="14" att_value="900"/>
  </titlelist>
  
</titlelist>